steamnews/__init__.py
steamnews/steamnews.py
steamnews-0.1.dist-info/LICENSE
steamnews-0.1.dist-info/METADATA
steamnews-0.1.dist-info/WHEEL
steamnews-0.1.dist-info/top_level.txt
steamnews-0.1.dist-info/RECORD
