Metadata-Version: 2.1
Name: steamnews
Version: 0.1
Summary: Wrapper for the SteamNews Webapi
Home-page: https://github.com/Kamigiri/steamnews
Author: Mert Demirbilek
Author-email: MertDemirbilek@outlook.de
License: MIT
Download-URL: https://pypi.org/project/steamnews/
Keywords: steam,steamnews,Steam News
Platform: UNKNOWN
License-File: LICENSE
Requires-Dist: requests
